dbt_core_mcp/__init__.py
dbt_core_mcp/__main__.py
dbt_core_mcp/server.py
dbt_core_mcp/dbt/__init__.py
dbt_core_mcp/dbt/bridge_runner.py
dbt_core_mcp/dbt/manifest.py
dbt_core_mcp/dbt/runner.py
dbt_core_mcp/utils/__init__.py
dbt_core_mcp/utils/env_detector.py
dbt_core_mcp/utils/process_check.py
dbt_core_mcp/utils/warehouse_adapter.py
dbt_core_mcp/utils/warehouse_databricks.py
dbt_core_mcp-1.3.2.dist-info/METADATA
dbt_core_mcp-1.3.2.dist-info/WHEEL
dbt_core_mcp-1.3.2.dist-info/entry_points.txt
dbt_core_mcp-1.3.2.dist-info/licenses/LICENSE
dbt_core_mcp-1.3.2.dist-info/RECORD
