Metadata-Version: 2.4
Name: dbt-core-mcp
Version: 1.3.2
Summary: DBT Core MCP Server: Interact with DBT projects via Model Context Protocol
Project-URL: Homepage, https://github.com/NiclasOlofsson/dbt-core-mcp
Project-URL: Repository, https://github.com/NiclasOlofsson/dbt-core-mcp
Project-URL: Issues, https://github.com/NiclasOlofsson/dbt-core-mcp/issues
Project-URL: Documentation, https://github.com/NiclasOlofsson/dbt-core-mcp#readme
Author-email: Niclas Olofsson <nicke.olofsson@gmail.com>
License: MIT
License-File: LICENSE
Keywords: analytics,data,dbt,dbt-core,mcp
Classifier: Development Status :: 5 - Production/Stable
Classifier: Intended Audience :: Developers
Classifier: License :: OSI Approved :: MIT License
Classifier: Programming Language :: Python :: 3
Classifier: Programming Language :: Python :: 3.10
Classifier: Programming Language :: Python :: 3.11
Classifier: Programming Language :: Python :: 3.12
Requires-Python: >=3.10
Requires-Dist: fastmcp>=2.11.0
Requires-Dist: mcp>=1.12.0
Requires-Dist: psutil>=5.9.0
Requires-Dist: pydantic>=2.0.0
Requires-Dist: pyyaml>=6.0
Requires-Dist: requests>=2.28.0
Requires-Dist: typing-extensions
